{"nbaplayer": {"foxsports(425)": {"domain_samples": 5, "domain_count": 1723126, "other_domain_samples": 10, "other_domain_count": 4250, "domain_average": 344625.2, "other_domain_average": 425.0, "allowed_count": 241240.63999999998}, "msnca(434)": {"domain_samples": 5, "domain_count": 607675, "other_domain_samples": 10, "other_domain_count": 4340, "domain_average": 121535.0, "other_domain_average": 434.0, "allowed_count": 85077.5}, "si(515)": {"domain_samples": 5, "domain_count": 2246436, "other_domain_samples": 10, "other_domain_count": 5150, "domain_average": 449287.2, "other_domain_average": 515.0, "allowed_count": 314504.04}}}